picksy/__init__.py
picksy/main.py
picksy-0.1.0.dist-info/LICENSE
picksy-0.1.0.dist-info/WHEEL
picksy-0.1.0.dist-info/METADATA
picksy-0.1.0.dist-info/RECORD
