Metadata-Version: 2.1
Name: picksy
Version: 0.1.0
Summary: Picksy. Python picker module with a simple search.
License: MIT
Author: Paul Glushak (hxii)
Author-email: paul@glushak.net
Requires-Python: >=3.8,<4.0
Classifier: License :: OSI Approved :: MIT License
Classifier: Programming Language :: Python :: 3
Classifier: Programming Language :: Python :: 3.10
Classifier: Programming Language :: Python :: 3.8
Classifier: Programming Language :: Python :: 3.9
